{
   "0" : {
      "protocols" : {
         "HTTP" : ""
      },
      "reason" : ""
   },
   "100" : {
      "conflict" : 1,
      "http" : {
         "id" : "section-6.2.1",
         "spec" : "RFC7231"
      },
      "iana" : {
         "HTTP" : 1,
         "RTSP" : 1,
         "SIP" : 1
      },
      "icap" : {
         "id" : "section-4.3.3",
         "spec" : "RFC3507"
      },
      "protocols" : {
         "HTTP" : "Continue",
         "Q4S" : "Trying",
         "RTSP" : "Continue",
         "SIP" : "Trying"
      },
      "reason" : "Continue"
   },
   "101" : {
      "http" : {
         "id" : "section-6.2.2",
         "spec" : "RFC7231"
      },
      "iana" : {
         "HTTP" : 1
      },
      "protocols" : {
         "HTTP" : "Switching Protocols"
      },
      "reason" : "Switching Protocols"
   },
   "102" : {
      "http" : {
         "id" : "section-10.1",
         "spec" : "RFC2518"
      },
      "iana" : {
         "HTTP" : 1
      },
      "protocols" : {
         "HTTP" : "Processing"
      },
      "reason" : "Processing"
   },
   "103" : {
      "conflict" : 1,
      "protocols" : {
         "HTTP" : "Access denied while creating Web Service"
      },
      "reason" : "Access denied while creating Web Service"
   },
   "104" : {
      "protocols" : {
         "HTTP" : "File Format or Program Error"
      },
      "reason" : "File Format or Program Error"
   },
   "122" : {
      "protocols" : {
         "HTTP" : "Request-URI too long"
      },
      "reason" : "Request-URI too long"
   },
   "180" : {
      "iana" : {
         "SIP" : 1
      },
      "protocols" : {
         "SIP" : "Ringing"
      },
      "reason" : "Ringing"
   },
   "181" : {
      "iana" : {
         "SIP" : 1
      },
      "protocols" : {
         "SIP" : "Call Is Being Forwarded"
      },
      "reason" : "Call Is Being Forwarded"
   },
   "182" : {
      "iana" : {
         "SIP" : 1
      },
      "protocols" : {
         "SIP" : "Queued"
      },
      "reason" : "Queued"
   },
   "183" : {
      "iana" : {
         "SIP" : 1
      },
      "protocols" : {
         "SIP" : "Session Progress"
      },
      "reason" : "Session Progress"
   },
   "199" : {
      "iana" : {
         "SIP" : 1
      },
      "protocols" : {
         "SIP" : "Early Dialog Terminated"
      },
      "reason" : "Early Dialog Terminated"
   },
   "200" : {
      "http" : {
         "cacheable" : 1,
         "id" : "section-6.3.1",
         "spec" : "RFC7231"
      },
      "iana" : {
         "HTTP" : 1,
         "RTSP" : 1,
         "SIP" : 1
      },
      "protocols" : {
         "CGI" : "OK",
         "HTTP" : "OK",
         "Q4S" : "OK",
         "RTSP" : "OK",
         "SIP" : "OK",
         "SSTP" : "OK",
         "mediaont-api" : "OK"
      },
      "reason" : "OK",
      "s-http" : {
         "id" : "section-2.3",
         "spec" : "RFC2660"
      },
      "ssdp" : {
         "url" : "http://upnp.org/specs/arch/UPnP-arch-DeviceArchitecture-v2.0.pdf#page=41"
      }
   },
   "201" : {
      "http" : {
         "id" : "section-6.3.2",
         "spec" : "RFC7231"
      },
      "iana" : {
         "HTTP" : 1,
         "RTSP" : 1
      },
      "protocols" : {
         "HTTP" : "Created",
         "RTSP" : "Created"
      },
      "reason" : "Created"
   },
   "202" : {
      "http" : {
         "id" : "section-6.3.3",
         "spec" : "RFC7231"
      },
      "iana" : {
         "HTTP" : 1,
         "SIP" : 1
      },
      "protocols" : {
         "HTTP" : "Accepted",
         "SIP" : "Accepted"
      },
      "reason" : "Accepted",
      "sip" : {
         "deprecated" : 1
      }
   },
   "203" : {
      "http" : {
         "cacheable" : 1,
         "id" : "section-6.3.4",
         "spec" : "RFC7231"
      },
      "iana" : {
         "HTTP" : 1
      },
      "protocols" : {
         "HTTP" : "Non-Authoritative Information"
      },
      "reason" : "Non-Authoritative Information"
   },
   "204" : {
      "conflict" : 1,
      "http" : {
         "cacheable" : 1,
         "id" : "section-6.3.5",
         "spec" : "RFC7231"
      },
      "iana" : {
         "HTTP" : 1,
         "SIP" : 1
      },
      "icap" : {
         "id" : "section-4.3.3",
         "spec" : "RFC3507"
      },
      "protocols" : {
         "HTTP" : "No Content",
         "SIP" : "No Notification",
         "SSTP" : "No Content",
         "mediaont-api" : "No Content"
      },
      "reason" : "No Content"
   },
   "205" : {
      "http" : {
         "id" : "section-6.3.6",
         "spec" : "RFC7231"
      },
      "iana" : {
         "HTTP" : 1
      },
      "protocols" : {
         "HTTP" : "Reset Content"
      },
      "reason" : "Reset Content"
   },
   "206" : {
      "http" : {
         "cacheable" : 1,
         "id" : "section-4.1",
         "spec" : "RFC7233"
      },
      "iana" : {
         "HTTP" : 1
      },
      "protocols" : {
         "HTTP" : "Partial Content",
         "mediaont-api" : "Partial Content"
      },
      "reason" : "Partial Content"
   },
   "207" : {
      "iana" : {
         "HTTP" : 1
      },
      "protocols" : {
         "HTTP" : "Multi-Status"
      },
      "reason" : "Multi-Status"
   },
   "208" : {
      "iana" : {
         "HTTP" : 1
      },
      "protocols" : {
         "HTTP" : "Already Reported"
      },
      "reason" : "Already Reported"
   },
   "210" : {
      "protocols" : {
         "SSTP" : "Break"
      },
      "reason" : "Break"
   },
   "220" : {
      "protocols" : {
         "HTTP" : "Uses Protocol Extensions"
      },
      "reason" : "Uses Protocol Extensions"
   },
   "226" : {
      "http" : {
         "cacheable" : 1,
         "id" : "section-10.4.1",
         "spec" : "RFC3229"
      },
      "iana" : {
         "HTTP" : 1
      },
      "protocols" : {
         "HTTP" : "IM Used"
      },
      "reason" : "IM Used"
   },
   "235" : {
      "http" : {
         "url" : "http://tools.ietf.org/html/draft-nystrom-http-sasl-12#page-20"
      },
      "protocols" : {
         "HTTP" : "Authentication Completed"
      },
      "reason" : "Authentication Completed"
   },
   "236" : {
      "http" : {
         "url" : "http://tools.ietf.org/html/draft-nystrom-http-sasl-12#page-20"
      },
      "protocols" : {
         "HTTP" : "Proxy Authentication Completed"
      },
      "reason" : "Proxy Authentication Completed"
   },
   "250" : {
      "iana" : {
         "RTSP" : 1
      },
      "protocols" : {
         "RTSP" : "Low on Storage Space"
      },
      "reason" : "Low on Storage Space"
   },
   "300" : {
      "http" : {
         "cacheable" : 1,
         "id" : "section-6.4.1",
         "redirect" : "true",
         "spec" : "RFC7231"
      },
      "iana" : {
         "HTTP" : 1,
         "RTSP" : 1,
         "SIP" : 1
      },
      "protocols" : {
         "HTTP" : "Multiple Choices",
         "RTSP" : "Multiple Choices",
         "SIP" : "Multiple Choices"
      },
      "reason" : "Multiple Choices"
   },
   "301" : {
      "http" : {
         "cacheable" : 1,
         "id" : "section-6.4.2",
         "redirect" : "true",
         "spec" : "RFC7231"
      },
      "iana" : {
         "HTTP" : 1,
         "RTSP" : 1,
         "SIP" : 1
      },
      "protocols" : {
         "HTTP" : "Moved Permanently",
         "RTSP" : "Moved Permanently",
         "SIP" : "Moved Permanently"
      },
      "reason" : "Moved Permanently"
   },
   "302" : {
      "conflict" : 1,
      "http" : {
         "id" : "section-6.4.3",
         "redirect" : "true",
         "spec" : "RFC7231"
      },
      "iana" : {
         "HTTP" : 1,
         "RTSP" : 1,
         "SIP" : 1
      },
      "protocols" : {
         "CGI" : "Found",
         "HTTP" : "Found",
         "RTSP" : "Moved Temporarily",
         "SIP" : "Moved Temporarily"
      },
      "reason" : "Found"
   },
   "303" : {
      "http" : {
         "id" : "section-6.4.4",
         "redirect" : "true",
         "spec" : "RFC7231"
      },
      "iana" : {
         "HTTP" : 1,
         "RTSP" : 1
      },
      "protocols" : {
         "HTTP" : "See Other",
         "RTSP" : "See Other",
         "SIP" : "See Other"
      },
      "reason" : "See Other"
   },
   "304" : {
      "http" : {
         "id" : "section-4.1",
         "redirect" : "false",
         "spec" : "RFC7232"
      },
      "iana" : {
         "HTTP" : 1,
         "RTSP" : 1
      },
      "protocols" : {
         "HTTP" : "Not Modified",
         "RTSP" : "Not Modified"
      },
      "reason" : "Not Modified"
   },
   "305" : {
      "http" : {
         "deprecated" : 1,
         "id" : "section-6.4.5",
         "redirect" : "false",
         "spec" : "RFC7231"
      },
      "iana" : {
         "HTTP" : 1,
         "RTSP" : 1,
         "SIP" : 1
      },
      "protocols" : {
         "HTTP" : "Use Proxy",
         "RTSP" : "Use Proxy",
         "SIP" : "Use Proxy"
      },
      "reason" : "Use Proxy"
   },
   "306" : {
      "conflict" : 1,
      "http" : {
         "id" : "section-6.4.6",
         "obsolete" : 1,
         "redirect" : "false",
         "spec" : "RFC7231"
      },
      "iana" : {
         "HTTP" : 1
      },
      "protocols" : {
         "HTTP" : "Switch Proxy"
      },
      "reason" : "Switch Proxy"
   },
   "307" : {
      "http" : {
         "id" : "section-6.4.7",
         "redirect" : "true",
         "spec" : "RFC7231"
      },
      "iana" : {
         "HTTP" : 1
      },
      "protocols" : {
         "HTTP" : "Temporary Redirect"
      },
      "reason" : "Temporary Redirect"
   },
   "308" : {
      "conflict" : 1,
      "http" : {
         "cacheable" : 1,
         "id" : "section-3",
         "redirect" : "true",
         "spec" : "RFC7238"
      },
      "iana" : {
         "HTTP" : 1
      },
      "protocols" : {
         "HTTP" : "Permanent Redirect"
      },
      "reason" : "Permanent Redirect"
   },
   "320" : {
      "protocols" : {
         "S-HTTP" : "SHTTP Not Modifed"
      },
      "reason" : "SHTTP Not Modifed",
      "s-http" : {
         "id" : "section-5.2.5",
         "spec" : "RFC2660"
      }
   },
   "350" : {
      "http" : {
         "obsolete" : 1,
         "url" : "http://tools.ietf.org/html/draft-girod-w3-id-res-ext-00#section-2.3"
      },
      "protocols" : {
         "HTTP" : "Resolution Delegated"
      },
      "reason" : "Resolution Delegated"
   },
   "380" : {
      "iana" : {
         "SIP" : 1
      },
      "protocols" : {
         "SIP" : "Alternative Service"
      },
      "reason" : "Alternative Service"
   },
   "400" : {
      "http" : {
         "id" : "section-6.5.1",
         "spec" : "RFC7231"
      },
      "iana" : {
         "HTTP" : 1,
         "RTSP" : 1,
         "SIP" : 1
      },
      "icap" : {
         "id" : "section-4.3.3",
         "spec" : "RFC3507"
      },
      "protocols" : {
         "CGI" : "Bad Request",
         "HTTP" : "Bad Request",
         "Q4S" : "Bad Request",
         "RTSP" : "Bad Request",
         "SIP" : "Bad Request",
         "SSTP" : "Bad Request",
         "mediaont-api" : "Bad Request"
      },
      "reason" : "Bad Request"
   },
   "401" : {
      "http" : {
         "id" : "section-3.1",
         "spec" : "RFC7235"
      },
      "iana" : {
         "HTTP" : 1,
         "RTSP" : 1,
         "SIP" : 1
      },
      "protocols" : {
         "HTTP" : "Unauthorized",
         "RTSP" : "Unauthorized",
         "SIP" : "Unauthorized"
      },
      "reason" : "Unauthorized"
   },
   "402" : {
      "http" : {
         "id" : "section-6.5.2",
         "reserved" : 1,
         "spec" : "RFC7231"
      },
      "iana" : {
         "HTTP" : 1,
         "RTSP" : 1,
         "SIP" : 1
      },
      "protocols" : {
         "HTTP" : "Payment Required",
         "RTSP" : "Payment Required",
         "SIP" : "Payment Required"
      },
      "reason" : "Payment Required"
   },
   "403" : {
      "http" : {
         "id" : "section-6.5.3",
         "spec" : "RFC7231"
      },
      "iana" : {
         "HTTP" : 1,
         "RTSP" : 1,
         "SIP" : 1
      },
      "protocols" : {
         "HTTP" : "Forbidden",
         "RTSP" : "Forbidden",
         "SIP" : "Forbidden"
      },
      "reason" : "Forbidden"
   },
   "404" : {
      "http" : {
         "cacheable" : 1,
         "id" : "section-6.5.4",
         "spec" : "RFC7231"
      },
      "iana" : {
         "HTTP" : 1,
         "RTSP" : 1,
         "SIP" : 1
      },
      "icap" : {
         "id" : "section-4.3.3",
         "spec" : "RFC3507"
      },
      "protocols" : {
         "HTTP" : "Not Found",
         "Q4S" : "Not Found",
         "RTSP" : "Not Found",
         "SIP" : "Not Found",
         "mediaont-api" : "Not Found"
      },
      "reason" : "Not Found"
   },
   "405" : {
      "http" : {
         "cacheable" : 1,
         "id" : "section-6.5.5",
         "spec" : "RFC7231"
      },
      "iana" : {
         "HTTP" : 1,
         "RTSP" : 1,
         "SIP" : 1
      },
      "icap" : {
         "id" : "section-4.3.3",
         "spec" : "RFC3507"
      },
      "protocols" : {
         "HTTP" : "Method Not Allowed",
         "Q4S" : "Method Not Allowed",
         "RTSP" : "Method Not Allowed",
         "SIP" : "Method Not Allowed"
      },
      "reason" : "Method Not Allowed"
   },
   "406" : {
      "http" : {
         "id" : "section-6.5.6",
         "spec" : "RFC7231"
      },
      "iana" : {
         "HTTP" : 1,
         "RTSP" : 1,
         "SIP" : 1
      },
      "protocols" : {
         "HTCPCP" : "Not Acceptable",
         "HTTP" : "Not Acceptable",
         "Q4S" : "Not Acceptable",
         "RTSP" : "Not Acceptable",
         "SIP" : "Not Acceptable"
      },
      "reason" : "Not Acceptable"
   },
   "407" : {
      "http" : {
         "id" : "section-3.2",
         "spec" : "RFC7235"
      },
      "iana" : {
         "HTTP" : 1,
         "RTSP" : 1,
         "SIP" : 1
      },
      "protocols" : {
         "HTTP" : "Proxy Authentication Required",
         "RTSP" : "Proxy Authentication Required",
         "SIP" : "Proxy Authentication Required"
      },
      "reason" : "Proxy Authentication Required"
   },
   "408" : {
      "conflict" : 1,
      "http" : {
         "id" : "section-6.5.7",
         "spec" : "RFC7231"
      },
      "iana" : {
         "HTTP" : 1,
         "RTSP" : 1,
         "SIP" : 1
      },
      "icap" : {
         "id" : "section-4.3.3",
         "spec" : "RFC3507"
      },
      "protocols" : {
         "HTTP" : "Request Timeout",
         "Q4S" : "Request Timeout",
         "RTSP" : "Request Time-out",
         "SIP" : "Request Timeout",
         "SSTP" : "Request Timeout"
      },
      "reason" : "Request Timeout"
   },
   "409" : {
      "http" : {
         "id" : "section-6.5.8",
         "spec" : "RFC7231"
      },
      "iana" : {
         "HTTP" : 1
      },
      "protocols" : {
         "HTTP" : "Conflict",
         "SIP" : "Conflict",
         "SSTP" : "Conflict"
      },
      "reason" : "Conflict"
   },
   "410" : {
      "http" : {
         "cacheable" : 1,
         "id" : "section-6.5.9",
         "spec" : "RFC7231"
      },
      "iana" : {
         "HTTP" : 1,
         "RTSP" : 1,
         "SIP" : 1
      },
      "protocols" : {
         "HTTP" : "Gone",
         "RTSP" : "Gone",
         "SIP" : "Gone"
      },
      "reason" : "Gone"
   },
   "411" : {
      "http" : {
         "id" : "section-6.5.10",
         "spec" : "RFC7231"
      },
      "iana" : {
         "HTTP" : 1,
         "RTSP" : 1
      },
      "protocols" : {
         "HTTP" : "Length Required",
         "RTSP" : "Length Required",
         "SIP" : "Length Required"
      },
      "reason" : "Length Required"
   },
   "412" : {
      "conflict" : 1,
      "http" : {
         "id" : "section-4.2",
         "spec" : "RFC7232"
      },
      "iana" : {
         "HTTP" : 1,
         "RTSP" : 1,
         "SIP" : 1
      },
      "protocols" : {
         "HTTP" : "Precondition Failed",
         "RTSP" : "Precondition Failed",
         "SIP" : "Conditional Request Failed"
      },
      "reason" : "Precondition Failed"
   },
   "413" : {
      "conflict" : 1,
      "http" : {
         "id" : "section-6.5.11",
         "spec" : "RFC7231"
      },
      "iana" : {
         "HTTP" : 1,
         "RTSP" : 1,
         "SIP" : 1
      },
      "protocols" : {
         "HTTP" : "Payload Too Large",
         "Q4S" : "Request Entity Too Large",
         "RTSP" : "Request Entity Too Large",
         "SIP" : "Request Entity Too Large"
      },
      "reason" : "Payload Too Large"
   },
   "414" : {
      "conflict" : 1,
      "http" : {
         "cacheable" : 1,
         "id" : "section-6.5.12",
         "spec" : "RFC7231"
      },
      "iana" : {
         "HTTP" : 1,
         "RTSP" : 1,
         "SIP" : 1
      },
      "protocols" : {
         "HTTP" : "URI Too Long",
         "Q4S" : "Request-URI Too Long",
         "RTSP" : "Request-URI Too Large",
         "SIP" : "Request-URI Too Long"
      },
      "reason" : "URI Too Long"
   },
   "415" : {
      "http" : {
         "id" : "section-6.5.13",
         "spec" : "RFC7231"
      },
      "iana" : {
         "HTTP" : 1,
         "RTSP" : 1,
         "SIP" : 1
      },
      "protocols" : {
         "HTTP" : "Unsupported Media Type",
         "Q4S" : "Unsupported Media Type",
         "RTSP" : "Unsupported Media Type",
         "SIP" : "Unsupported Media Type",
         "mediaont-api" : "Unsupported Media Type"
      },
      "reason" : "Unsupported Media Type"
   },
   "416" : {
      "conflict" : 1,
      "http" : {
         "id" : "section-4.4",
         "spec" : "RFC7233"
      },
      "iana" : {
         "HTTP" : 1,
         "SIP" : 1
      },
      "protocols" : {
         "HTTP" : "Range Not Satisfiable",
         "Q4S" : "Unsupported URI Scheme",
         "SIP" : "Unsupported URI Scheme"
      },
      "reason" : "Range Not Satisfiable"
   },
   "417" : {
      "conflict" : 1,
      "http" : {
         "id" : "section-6.5.14",
         "spec" : "RFC7231"
      },
      "iana" : {
         "HTTP" : 1,
         "SIP" : 1
      },
      "protocols" : {
         "HTTP" : "Expectation Failed",
         "SIP" : "Unknown Resource-Priority"
      },
      "reason" : "Expectation Failed"
   },
   "418" : {
      "http" : {
         "id" : "section-2.3.2",
         "spec" : "RFC2324"
      },
      "protocols" : {
         "HTCPCP" : "I'm a teapot"
      },
      "reason" : "I'm a teapot"
   },
   "419" : {
      "conflict" : 1,
      "protocols" : {
         "HTTP" : "Authentication Timeout"
      },
      "reason" : "Authentication Timeout"
   },
   "420" : {
      "conflict" : 1,
      "http" : {
         "id" : "section-5.2.2",
         "spec" : "RFC2660"
      },
      "iana" : {
         "SIP" : 1
      },
      "protocols" : {
         "HTTP" : "Policy Not Fulfilled",
         "S-HTTP" : "SecurityRetry",
         "SIP" : "Bad Extension",
         "SSTP" : "Refuse"
      },
      "reason" : "Policy Not Fulfilled",
      "s-http" : {
         "id" : "section-5.2.2",
         "spec" : "RFC2660"
      }
   },
   "421" : {
      "conflict" : 1,
      "http" : {
         "obsolete" : 1,
         "url" : "http://www.w3.org/TR/WD-http-pep#_Toc404743961"
      },
      "iana" : {
         "HTTP" : 1,
         "SIP" : 1
      },
      "protocols" : {
         "HTTP" : "Misdirected Request",
         "S-HTTP" : "BogusHeader",
         "SIP" : "Extension Required"
      },
      "reason" : "Misdirected Request",
      "s-http" : {
         "id" : "section-5.2.3",
         "spec" : "RFC2660"
      }
   },
   "422" : {
      "conflict" : 1,
      "http" : {
         "id" : "section-11.2",
         "spec" : "RFC4918"
      },
      "iana" : {
         "HTTP" : 1,
         "SIP" : 1
      },
      "protocols" : {
         "HTTP" : "Unprocessable Entity",
         "S-HTTP" : "SHTTP Proxy Authentication Required",
         "SIP" : "Session Interval Too Small"
      },
      "reason" : "Unprocessable Entity",
      "s-http" : {
         "id" : "section-5.2.4",
         "spec" : "RFC2660"
      }
   },
   "423" : {
      "conflict" : 1,
      "http" : {
         "id" : "section-11.3",
         "spec" : "RFC4918"
      },
      "iana" : {
         "HTTP" : 1,
         "SIP" : 1
      },
      "protocols" : {
         "HTTP" : "Locked",
         "SIP" : "Interval Too Brief"
      },
      "reason" : "Locked"
   },
   "424" : {
      "conflict" : 1,
      "http" : {
         "id" : "section-11.4",
         "spec" : "RFC4918"
      },
      "iana" : {
         "HTTP" : 1,
         "SIP" : 1
      },
      "protocols" : {
         "HTTP" : "Failed Dependency",
         "SIP" : "Bad Location Information"
      },
      "reason" : "Failed Dependency"
   },
   "425" : {
      "protocols" : {
         "HTTP" : "Unordered Collection"
      },
      "reason" : "Unordered Collection"
   },
   "426" : {
      "conflict" : 1,
      "http" : {
         "id" : "section-6.5.15",
         "spec" : "RFC7231"
      },
      "iana" : {
         "HTTP" : 1
      },
      "protocols" : {
         "HTTP" : "Upgrade Required"
      },
      "reason" : "Upgrade Required"
   },
   "427" : {
      "protocols" : {
         "HTTP" : "SOAPAction"
      },
      "reason" : "SOAPAction"
   },
   "428" : {
      "conflict" : 1,
      "iana" : {
         "HTTP" : 1,
         "SIP" : 1
      },
      "protocols" : {
         "HTTP" : "Precondition Required",
         "SIP" : "Use Identity Header"
      },
      "reason" : "Precondition Required"
   },
   "429" : {
      "conflict" : 1,
      "iana" : {
         "HTTP" : 1,
         "SIP" : 1
      },
      "protocols" : {
         "HTTP" : "Too Many Requests",
         "SIP" : "Provide Referrer Identity"
      },
      "reason" : "Too Many Requests"
   },
   "430" : {
      "conflict" : 1,
      "iana" : {
         "SIP" : 1
      },
      "protocols" : {
         "HTTP" : "WOULD BLOCK",
         "SIP" : "Flow Failed"
      },
      "reason" : "WOULD BLOCK"
   },
   "431" : {
      "iana" : {
         "HTTP" : 1
      },
      "protocols" : {
         "HTTP" : "Request Header Fields Too Large"
      },
      "reason" : "Request Header Fields Too Large"
   },
   "432" : {
      "http" : {
         "url" : "http://tools.ietf.org/html/draft-nystrom-http-sasl-12#page-20"
      },
      "protocols" : {
         "HTTP" : "Transition Needed"
      },
      "reason" : "Transition Needed"
   },
   "433" : {
      "iana" : {
         "SIP" : 1
      },
      "protocols" : {
         "SIP" : "Anonymity Disallowed"
      },
      "reason" : "Anonymity Disallowed"
   },
   "436" : {
      "iana" : {
         "SIP" : 1
      },
      "protocols" : {
         "SIP" : "Bad Identity-Info"
      },
      "reason" : "Bad Identity-Info"
   },
   "437" : {
      "iana" : {
         "SIP" : 1
      },
      "protocols" : {
         "SIP" : "Unsupported Certificate"
      },
      "reason" : "Unsupported Certificate"
   },
   "438" : {
      "iana" : {
         "SIP" : 1
      },
      "protocols" : {
         "SIP" : "Invalid Identity Header"
      },
      "reason" : "Invalid Identity Header"
   },
   "439" : {
      "iana" : {
         "SIP" : 1
      },
      "protocols" : {
         "SIP" : "First Hop Lacks Outbound Support"
      },
      "reason" : "First Hop Lacks Outbound Support"
   },
   "440" : {
      "conflict" : 1,
      "iana" : {
         "SIP" : 1
      },
      "protocols" : {
         "HTTP" : "Login Timeout",
         "SIP" : "Max-Breadth Exceeded"
      },
      "reason" : "Login Timeout"
   },
   "444" : {
      "protocols" : {
         "HTTP" : "No Response"
      },
      "reason" : "No Response"
   },
   "449" : {
      "protocols" : {
         "HTTP" : "Retry With"
      },
      "reason" : "Retry With"
   },
   "450" : {
      "conflict" : 1,
      "http" : {
         "url" : "http://tools.ietf.org/html/draft-nystrom-http-sasl-12#page-20"
      },
      "protocols" : {
         "HTTP" : "Authentication mechanism not accepted"
      },
      "reason" : "Authentication mechanism not accepted"
   },
   "451" : {
      "conflict" : 1,
      "iana" : {
         "RTSP" : 1
      },
      "protocols" : {
         "HTTP" : "Redirect",
         "RTSP" : "Parameter Not Understood"
      },
      "reason" : "Redirect"
   },
   "452" : {
      "iana" : {
         "RTSP" : 1
      },
      "protocols" : {
         "RTSP" : "Conference Not Found"
      },
      "reason" : "Conference Not Found"
   },
   "453" : {
      "iana" : {
         "RTSP" : 1
      },
      "protocols" : {
         "RTSP" : "Not Enough Bandwidth"
      },
      "reason" : "Not Enough Bandwidth"
   },
   "454" : {
      "iana" : {
         "RTSP" : 1
      },
      "protocols" : {
         "RTSP" : "Session Not Found"
      },
      "reason" : "Session Not Found"
   },
   "455" : {
      "iana" : {
         "RTSP" : 1
      },
      "protocols" : {
         "RTSP" : "Method Not Valid in This State"
      },
      "reason" : "Method Not Valid in This State"
   },
   "456" : {
      "iana" : {
         "RTSP" : 1
      },
      "protocols" : {
         "RTSP" : "Header Field Not Valid for Resource"
      },
      "reason" : "Header Field Not Valid for Resource"
   },
   "457" : {
      "iana" : {
         "RTSP" : 1
      },
      "protocols" : {
         "RTSP" : "Invalid Range"
      },
      "reason" : "Invalid Range"
   },
   "458" : {
      "iana" : {
         "RTSP" : 1
      },
      "protocols" : {
         "RTSP" : "Parameter Is Read-Only"
      },
      "reason" : "Parameter Is Read-Only"
   },
   "459" : {
      "iana" : {
         "RTSP" : 1
      },
      "protocols" : {
         "RTSP" : "Aggregate operation not allowed"
      },
      "reason" : "Aggregate operation not allowed"
   },
   "460" : {
      "iana" : {
         "RTSP" : 1
      },
      "protocols" : {
         "RTSP" : "Only aggregate operation allowed"
      },
      "reason" : "Only aggregate operation allowed"
   },
   "461" : {
      "iana" : {
         "RTSP" : 1
      },
      "protocols" : {
         "RTSP" : "Unsupported transport"
      },
      "reason" : "Unsupported transport"
   },
   "462" : {
      "conflict" : 1,
      "iana" : {
         "RTSP" : 1
      },
      "protocols" : {
         "RTSP" : "Destination unreachable",
         "mediaont-api" : "Property not defined in Source Format"
      },
      "reason" : "Destination unreachable"
   },
   "463" : {
      "iana" : {
         "RTSP" : 1
      },
      "protocols" : {
         "RTSP" : "Key management Failure"
      },
      "reason" : "Key management Failure"
   },
   "469" : {
      "iana" : {
         "SIP" : 1
      },
      "protocols" : {
         "SIP" : "Bad Info Package"
      },
      "reason" : "Bad Info Package"
   },
   "470" : {
      "iana" : {
         "SIP" : 1
      },
      "protocols" : {
         "SIP" : "Consent Needed"
      },
      "reason" : "Consent Needed"
   },
   "480" : {
      "conflict" : 1,
      "iana" : {
         "SIP" : 1
      },
      "protocols" : {
         "SIP" : "Temporarily Unavailable"
      },
      "reason" : "Temporarily Unavailable"
   },
   "481" : {
      "conflict" : 1,
      "iana" : {
         "SIP" : 1
      },
      "protocols" : {
         "SIP" : "Call/Transaction Does Not Exist"
      },
      "reason" : "Call/Transaction Does Not Exist"
   },
   "482" : {
      "iana" : {
         "SIP" : 1
      },
      "protocols" : {
         "SIP" : "Loop Detected"
      },
      "reason" : "Loop Detected"
   },
   "483" : {
      "iana" : {
         "SIP" : 1
      },
      "protocols" : {
         "SIP" : "Too Many Hops"
      },
      "reason" : "Too Many Hops"
   },
   "484" : {
      "conflict" : 1,
      "iana" : {
         "SIP" : 1
      },
      "protocols" : {
         "SIP" : "Address Incomplete"
      },
      "reason" : "Address Incomplete"
   },
   "485" : {
      "iana" : {
         "SIP" : 1
      },
      "protocols" : {
         "SIP" : "Ambiguous"
      },
      "reason" : "Ambiguous"
   },
   "486" : {
      "iana" : {
         "SIP" : 1
      },
      "protocols" : {
         "SIP" : "Busy Here"
      },
      "reason" : "Busy Here"
   },
   "487" : {
      "conflict" : 1,
      "iana" : {
         "SIP" : 1
      },
      "protocols" : {
         "SIP" : "Request Terminated"
      },
      "reason" : "Request Terminated"
   },
   "488" : {
      "iana" : {
         "SIP" : 1
      },
      "protocols" : {
         "SIP" : "Not Acceptable Here"
      },
      "reason" : "Not Acceptable Here"
   },
   "489" : {
      "iana" : {
         "SIP" : 1
      },
      "protocols" : {
         "SIP" : "Bad Event"
      },
      "reason" : "Bad Event"
   },
   "491" : {
      "iana" : {
         "SIP" : 1
      },
      "protocols" : {
         "SIP" : "Request Pending"
      },
      "reason" : "Request Pending"
   },
   "493" : {
      "iana" : {
         "SIP" : 1
      },
      "protocols" : {
         "SIP" : "Undecipherable"
      },
      "reason" : "Undecipherable"
   },
   "494" : {
      "conflict" : 1,
      "iana" : {
         "SIP" : 1
      },
      "protocols" : {
         "HTTP" : "Request Header Too Large",
         "SIP" : "Security Agreement Required"
      },
      "reason" : "Request Header Too Large"
   },
   "495" : {
      "protocols" : {
         "HTTP" : "Cert Error"
      },
      "reason" : "Cert Error"
   },
   "496" : {
      "protocols" : {
         "HTTP" : "No Cert"
      },
      "reason" : "No Cert"
   },
   "497" : {
      "protocols" : {
         "HTTP" : "HTTP to HTTPS"
      },
      "reason" : "HTTP to HTTPS"
   },
   "498" : {
      "protocols" : {
         "HTTP" : "Token expired/invalid"
      },
      "reason" : "Token expired/invalid"
   },
   "499" : {
      "conflict" : 1,
      "protocols" : {
         "HTTP" : "Token required"
      },
      "reason" : "Token required"
   },
   "500" : {
      "conflict" : 1,
      "http" : {
         "id" : "section-6.6.1",
         "spec" : "RFC7231"
      },
      "iana" : {
         "HTTP" : 1,
         "RTSP" : 1,
         "SIP" : 1
      },
      "icap" : {
         "id" : "section-4.3.3",
         "spec" : "RFC3507"
      },
      "protocols" : {
         "HTTP" : "Internal Server Error",
         "Q4S" : "Server Internal Error",
         "RTSP" : "Internal Server Error",
         "SIP" : "Server Internal Error",
         "mediaont-api" : "Internal Server Error"
      },
      "reason" : "Internal Server Error"
   },
   "501" : {
      "http" : {
         "cacheable" : 1,
         "id" : "section-6.6.2",
         "spec" : "RFC7231"
      },
      "iana" : {
         "HTTP" : 1,
         "RTSP" : 1,
         "SIP" : 1
      },
      "icap" : {
         "id" : "section-4.3.3",
         "spec" : "RFC3507"
      },
      "protocols" : {
         "CGI" : "Not Implemented",
         "HTTP" : "Not Implemented",
         "Q4S" : "Not Implemented",
         "RTSP" : "Not Implemented",
         "SIP" : "Not Implemented",
         "SSTP" : "Not Implemented"
      },
      "reason" : "Not Implemented"
   },
   "502" : {
      "http" : {
         "id" : "section-6.6.3",
         "spec" : "RFC7231"
      },
      "iana" : {
         "HTTP" : 1,
         "RTSP" : 1,
         "SIP" : 1
      },
      "icap" : {
         "id" : "section-4.3.3",
         "spec" : "RFC3507"
      },
      "protocols" : {
         "HTTP" : "Bad Gateway",
         "RTSP" : "Bad Gateway",
         "SIP" : "Bad Gateway"
      },
      "reason" : "Bad Gateway"
   },
   "503" : {
      "http" : {
         "id" : "section-6.6.4",
         "spec" : "RFC7231"
      },
      "iana" : {
         "HTTP" : 1,
         "RTSP" : 1,
         "SIP" : 1
      },
      "icap" : {
         "id" : "section-4.3.3",
         "spec" : "RFC3507"
      },
      "protocols" : {
         "HTTP" : "Service Unavailable",
         "Q4S" : "Service Unavailable",
         "RTSP" : "Service Unavailable",
         "SIP" : "Service Unavailable",
         "SSTP" : "Service Unavailable"
      },
      "reason" : "Service Unavailable"
   },
   "504" : {
      "conflict" : 1,
      "http" : {
         "id" : "section-6.6.5",
         "spec" : "RFC7231"
      },
      "iana" : {
         "HTTP" : 1,
         "RTSP" : 1,
         "SIP" : 1
      },
      "protocols" : {
         "HTTP" : "Gateway Timeout",
         "Q4S" : "Server Time-out",
         "RTSP" : "Gateway Time-out",
         "SIP" : "Server Time-out"
      },
      "reason" : "Gateway Timeout"
   },
   "505" : {
      "conflict" : 1,
      "http" : {
         "id" : "section-6.6.6",
         "spec" : "RFC7231"
      },
      "iana" : {
         "HTTP" : 1,
         "RTSP" : 1,
         "SIP" : 1
      },
      "icap" : {
         "id" : "section-4.3.3",
         "spec" : "RFC3507"
      },
      "protocols" : {
         "HTTP" : "HTTP Version Not Supported",
         "Q4S" : "Version Not Supported",
         "RTSP" : "RTSP Version not supported",
         "SIP" : "Version Not Supported"
      },
      "reason" : "HTTP Version Not Supported"
   },
   "506" : {
      "iana" : {
         "HTTP" : 1
      },
      "protocols" : {
         "HTTP" : "Variant Also Negotiates"
      },
      "reason" : "Variant Also Negotiates"
   },
   "507" : {
      "http" : {
         "id" : "section-11.5",
         "spec" : "RFC4918"
      },
      "iana" : {
         "HTTP" : 1
      },
      "protocols" : {
         "HTTP" : "Insufficient Storage"
      },
      "reason" : "Insufficient Storage"
   },
   "508" : {
      "conflict" : 1,
      "iana" : {
         "HTTP" : 1
      },
      "protocols" : {
         "HTTP" : "Loop Detected"
      },
      "reason" : "Loop Detected"
   },
   "509" : {
      "protocols" : {
         "HTTP" : "Bandwidth Limit Exceeded"
      },
      "reason" : "Bandwidth Limit Exceeded"
   },
   "510" : {
      "conflict" : 1,
      "iana" : {
         "HTTP" : 1
      },
      "protocols" : {
         "HTTP" : "Not Extended",
         "SSTP" : "Not Local IP"
      },
      "reason" : "Not Extended"
   },
   "511" : {
      "conflict" : 1,
      "iana" : {
         "HTTP" : 1
      },
      "protocols" : {
         "HTTP" : "Network Authentication Required",
         "SSTP" : "In Black List"
      },
      "reason" : "Network Authentication Required"
   },
   "512" : {
      "protocols" : {
         "SSTP" : "Invisible"
      },
      "reason" : "Invisible"
   },
   "513" : {
      "iana" : {
         "SIP" : 1
      },
      "protocols" : {
         "Q4S" : "Message Too Large",
         "SIP" : "Message Too Large"
      },
      "reason" : "Message Too Large"
   },
   "520" : {
      "conflict" : 1,
      "protocols" : {
         "HTTP" : "Protocol Extension Error"
      },
      "reason" : "Protocol Extension Error"
   },
   "521" : {
      "protocols" : {
         "HTTP" : "Protocol Extension Not Implemented"
      },
      "reason" : "Protocol Extension Not Implemented"
   },
   "522" : {
      "conflict" : 1,
      "protocols" : {
         "HTTP" : "Protocol Extension Parameters Not Acceptable"
      },
      "reason" : "Protocol Extension Parameters Not Acceptable"
   },
   "523" : {
      "protocols" : {
         "HTTP" : ""
      },
      "reason" : ""
   },
   "524" : {
      "protocols" : {
         "HTTP" : "Origin Time-out"
      },
      "reason" : "Origin Time-out"
   },
   "551" : {
      "iana" : {
         "RTSP" : 1
      },
      "protocols" : {
         "RTSP" : "Option not supported"
      },
      "reason" : "Option not supported"
   },
   "562" : {
      "protocols" : {
         "mediaont-api" : "Property not supported"
      },
      "reason" : "Property not supported"
   },
   "580" : {
      "iana" : {
         "SIP" : 1
      },
      "protocols" : {
         "SIP" : "Precondition Failure"
      },
      "reason" : "Precondition Failure"
   },
   "595" : {
      "protocols" : {
         "HTTP" : ""
      },
      "reason" : ""
   },
   "596" : {
      "protocols" : {
         "HTTP" : ""
      },
      "reason" : ""
   },
   "597" : {
      "protocols" : {
         "HTTP" : ""
      },
      "reason" : ""
   },
   "598" : {
      "protocols" : {
         "HTTP" : "Network read timeout error"
      },
      "reason" : "Network read timeout error"
   },
   "599" : {
      "protocols" : {
         "HTTP" : "Network connect timeout error"
      },
      "reason" : "Network connect timeout error"
   },
   "600" : {
      "conflict" : 1,
      "iana" : {
         "SIP" : 1
      },
      "protocols" : {
         "Q4S" : "session does not exist",
         "SIP" : "Busy Everywhere"
      },
      "reason" : "Busy Everywhere"
   },
   "601" : {
      "protocols" : {
         "Q4S" : "quality level not allowed"
      },
      "reason" : "quality level not allowed"
   },
   "603" : {
      "conflict" : 1,
      "iana" : {
         "SIP" : 1
      },
      "protocols" : {
         "Q4S" : "Session not allowed",
         "SIP" : "Decline"
      },
      "reason" : "Decline"
   },
   "604" : {
      "conflict" : 1,
      "iana" : {
         "SIP" : 1
      },
      "protocols" : {
         "Q4S" : "authorization not allowed",
         "SIP" : "Does Not Exist Anywhere"
      },
      "reason" : "Does Not Exist Anywhere"
   },
   "606" : {
      "iana" : {
         "SIP" : 1
      },
      "protocols" : {
         "SIP" : "Not Acceptable"
      },
      "reason" : "Not Acceptable"
   }
}
